{"customer_id": 1001, "customer_name": "Logan Ellis", "date_of_birth": "1961-12-09", "telephone": "+1 3321819600", "email": "logan.ellis12@yahoo.com", "created_date": "2024-10-01"}
{"customer_id": 1002, "customer_name": "Avery Tran", "date_of_birth": "1998-01-18", "telephone": "+1 3863794026", "email": "avery.tran44@outlook.com", "created_date": "2024-10-01"}
{"customer_id": 1003, "customer_name": "Casey Hayes", "date_of_birth": "1981-02-03", "telephone": "+1 6155940781", "email": "casey.hayes49@gmail.com", "created_date": "2024-10-01"}
{"customer_id": 1004, "customer_name": "Finley Lawson", "date_of_birth": "2000-10-28", "telephone": "+1 5931034131", "email": "finley.lawson49@outlook.com", "created_date": "2024-10-01"}
{"customer_id": 1005, "customer_name": "Rowan Young", "date_of_birth": "1983-03-12", "telephone": "+1 5341928327", "email": "rowan.young49@outlook.com", "created_date": "2024-10-01"}
{"customer_id": 1006, "customer_name": "Nadia Young", "date_of_birth": "2004-09-08", "telephone": "+1 5030564139", "email": "nadia.young92@outlook.com", "created_date": "2024-10-01"}
{"customer_id": 1007, "customer_name": "Jamie Young", "date_of_birth": "1991-07-21", "telephone": "+1 7242388496", "email": "jamie.young75@hotmail.com", "created_date": "2024-10-01"}
{"customer_id": 1008, "customer_name": "Reese Jensen", "date_of_birth": "1968-09-16", "telephone": "+1 1012269166", "email": "reese.jensen77@hotmail.com", "created_date": "2024-10-01"}
{"customer_id": 1009, "customer_name": "Emerson Klein", "date_of_birth": "1995-01-22", "telephone": "+1 1845146270", "email": "emerson.klein93@outlook.com", "created_date": "2024-10-01"}
{"customer_id": 1010, "customer_name": "Emerson Donovan", "date_of_birth": "1971-09-04", "telephone": "+1 4893252880", "email": "emerson.donovan77@outlook.com", "created_date": "2024-10-01"}
